{
  "Beaver": [
    "Rodent",
    "Otter",
    "Moose",
    "Squirrel",
    "Capybara"
  ],
  "Delta": [
    "Yangtze",
    "Tributary",
    "Basin",
    "Irrawaddy",
    "Mekong"
  ],
  "Elmwood": [
    "Elm",
    "Riverdale",
    "Woodlawn",
    "Riverview",
    "Lakeview"
  ],
  "Emerald": [
    "Gemstone",
    "Gem",
    "Ruby",
    "Green",
    "Beryl"
  ],
  "Flax": [
    "Linen",
    "Linum",
    "Hemp",
    "Herb",
    "Barley"
  ],
  "Granite": [
    "Quartz",
    "Limestone",
    "Basalt",
    "Stone",
    "Marble"
  ],
  "Grime": [
    "Filth",
    "Dirt",
    "Dirty",
    "Grease",
    "Foul"
  ],
  "Ivory": [
    "Tusk",
    "Pearl",
    "Dentine",
    "Tusks",
    "Narwhal"
  ],
  "Lily": [
    "Daisy",
    "Flower",
    "Jasmine",
    "Raceme",
    "Fritillaria"
  ],
  "Noble": [
    "Royal",
    "Nobility",
    "Lord",
    "Honorable",
    "Grand"
  ],
  "Railway": [
    "Rail",
    "Railroad",
    "Track",
    "Tram",
    "Line"
  ],
  "Ranger": [
    "Firefighter",
    "Commando",
    "Sergeant",
    "Commander",
    "Hunter"
  ],
  "Ruby": [
    "Sapphire",
    "Red",
    "Emerald",
    "Scarlet",
    "Crimson"
  ],
  "Starlight": [
    "Moonlight",
    "Light",
    "Sunlight",
    "Sun",
    "Luminosity"
  ],
  "Terrace": [
    "Patio",
    "Balcony",
    "Veranda",
    "Courtyard",
    "Garden"
  ]
}
